alibabacloud_actiontrail20171204/__init__.py
alibabacloud_actiontrail20171204/client.py
alibabacloud_actiontrail20171204/models.py
alibabacloud_actiontrail20171204-1.0.2.dist-info/LICENSE
alibabacloud_actiontrail20171204-1.0.2.dist-info/METADATA
alibabacloud_actiontrail20171204-1.0.2.dist-info/WHEEL
alibabacloud_actiontrail20171204-1.0.2.dist-info/top_level.txt
alibabacloud_actiontrail20171204-1.0.2.dist-info/RECORD
